sdsu/__init__.py
sdsu/security/certificate.pem
sdsu/security/credentials.csv
sdsu/security/key.pem
sdsu/static/index.css
sdsu/static/index.html
sdsu/static/splash.html
sdsu-1.0.0.dist-info/METADATA
sdsu-1.0.0.dist-info/WHEEL
sdsu-1.0.0.dist-info/top_level.txt
sdsu-1.0.0.dist-info/RECORD
