Metadata-Version: 2.1
Name: sdsu
Version: 1.0.0
Summary: Skim milk. Gummy bears. Pure genius.
Home-page: https://github.com/Tythos/sdsu
Author: Brian Kirkpatrick
Author-email: code@tythos.net
License: BSD
Keywords: tornado static web server secure websocket
Platform: UNKNOWN
Classifier: Development Status :: 4 - Beta
Classifier: Environment :: Console
Classifier: Intended Audience :: Developers
Classifier: Intended Audience :: Information Technology
Classifier: Intended Audience :: System Administrators
Classifier: License :: OSI Approved :: BSD License
Classifier: Operating System :: OS Independent
Classifier: Topic :: Internet :: WWW/HTTP
Classifier: Programming Language :: Python :: 3
Requires-Dist: tornado (>=5.0.0)
